huaweicloudsdkoroas/__init__.py
huaweicloudsdkoroas/v1/__init__.py
huaweicloudsdkoroas/v1/oroas_async_client.py
huaweicloudsdkoroas/v1/oroas_client.py
huaweicloudsdkoroas/v1/model/__init__.py
huaweicloudsdkoroas/v1/model/create_task_request.py
huaweicloudsdkoroas/v1/model/create_task_response.py
huaweicloudsdkoroas/v1/model/delete_task_request.py
huaweicloudsdkoroas/v1/model/delete_task_response.py
huaweicloudsdkoroas/v1/model/list_task_request.py
huaweicloudsdkoroas/v1/model/list_task_response.py
huaweicloudsdkoroas/v1/model/show_task_request.py
huaweicloudsdkoroas/v1/model/show_task_response.py
huaweicloudsdkoroas/v1/model/task_dto.py
huaweicloudsdkoroas/v1/model/task_list_item_vo.py
huaweicloudsdkoroas/v1/region/__init__.py
huaweicloudsdkoroas/v1/region/oroas_region.py
huaweicloudsdkoroas-3.1.184.dist-info/METADATA
huaweicloudsdkoroas-3.1.184.dist-info/WHEEL
huaweicloudsdkoroas-3.1.184.dist-info/licenses/LICENSE
huaweicloudsdkoroas-3.1.184.dist-info/RECORD
